bluesky_live/__init__.py
bluesky_live/_utils.py
bluesky_live/_version.py
bluesky_live/bluesky_run.py
bluesky_live/conversion.py
bluesky_live/document.py
bluesky_live/event.py
bluesky_live/list.py
bluesky_live/run_builder.py
bluesky_live/tests/__init__.py
bluesky_live/tests/conftest.py
bluesky_live/tests/test_bluesky_run.py
bluesky_live/tests/test_build_from_docs.py
bluesky_live/tests/test_run_builder.py
bluesky_live-0.0.8.dist-info/AUTHORS.rst
bluesky_live-0.0.8.dist-info/LICENSE
bluesky_live-0.0.8.dist-info/METADATA
bluesky_live-0.0.8.dist-info/WHEEL
bluesky_live-0.0.8.dist-info/entry_points.txt
bluesky_live-0.0.8.dist-info/top_level.txt
bluesky_live-0.0.8.dist-info/RECORD
