Metadata-Version: 1.2
Name: bluesky-live
Version: 0.0.8
Summary: Prototype building blocks for working with streaming data in bluesky
Home-page: https://github.com/bluesky/bluesky-live
Author: Brookhaven National Laboratory
Author-email: dallan@bnl.gov
License: BSD (3-clause)
Platform: UNKNOWN
Classifier: Development Status :: 2 - Pre-Alpha
Classifier: Natural Language :: English
Classifier: Programming Language :: Python :: 3
Requires-Python: >=3.6
